{
  "version": 1,
  "name": "Стойка Луффи §5(§dМульти вселенная§5) §8(One Piece)",
  "description": "Много мяса, нет салата — это завтрак для пирата",
  "author": "SPEmotes",
  "emote": {
    "beginTick": 0,
    "endTick": 69,
    "stopTick": 70,
    "isLoop": true,
    "returnTick": 8,
    "nsfw": false,
    "degrees": false,
    "moves": [
      {
        "tick": 8,
        "easing": "INOUTQUAD",
        "head": {
          "x": -0.0
        }
      },
      {
        "tick": 69,
        "easing": "INOUTQUAD",
        "head": {
          "x": -0.0
        }
      },
      {
        "tick": 8,
        "easing": "INOUTQUAD",
        "head": {
          "y": -0.0
        }
      },
      {
        "tick": 69,
        "easing": "INOUTQUAD",
        "head": {
          "y": -0.0
        }
      },
      {
        "tick": 8,
        "easing": "INOUTQUAD",
        "head": {
          "z": -0.0
        }
      },
      {
        "tick": 69,
        "easing": "INOUTQUAD",
        "head": {
          "z": -0.0
        }
      },
      {
        "tick": 8,
        "easing": "INOUTQUAD",
        "head": {
          "pitch": -0.46871313
        }
      },
      {
        "tick": 27,
        "easing": "INOUTQUAD",
        "head": {
          "pitch": -0.648855
        }
      },
      {
        "tick": 69,
        "easing": "INOUTQUAD",
        "head": {
          "pitch": -0.46871313
        }
      },
      {
        "tick": 8,
        "easing": "INOUTQUAD",
        "head": {
          "yaw": 0.37054956
        }
      },
      {
        "tick": 27,
        "easing": "INOUTQUAD",
        "head": {
          "yaw": 0.37484905
        }
      },
      {
        "tick": 69,
        "easing": "INOUTQUAD",
        "head": {
          "yaw": 0.37054956
        }
      },
      {
        "tick": 8,
        "easing": "INOUTQUAD",
        "head": {
          "roll": -0.074480094
        }
      },
      {
        "tick": 27,
        "easing": "INOUTQUAD",
        "head": {
          "roll": -0.08692213
        }
      },
      {
        "tick": 69,
        "easing": "INOUTQUAD",
        "head": {
          "roll": -0.074480094
        }
      },
      {
        "tick": 3,
        "easing": "INOUTQUAD",
        "rightLeg": {
          "x": -2.3819861
        }
      },
      {
        "tick": 8,
        "easing": "INOUTQUAD",
        "rightLeg": {
          "x": -3.423314
        }
      },
      {
        "tick": 42,
        "easing": "INOUTQUAD",
        "rightLeg": {
          "x": -3.4019775
        }
      },
      {
        "tick": 69,
        "easing": "INOUTQUAD",
        "rightLeg": {
          "x": -3.423314
        }
      },
      {
        "tick": 3,
        "easing": "INOUTQUAD",
        "rightLeg": {
          "y": 11.66421
        }
      },
      {
        "tick": 8,
        "easing": "INOUTQUAD",
        "rightLeg": {
          "y": 10.938739
        }
      },
      {
        "tick": 42,
        "easing": "INOUTQUAD",
        "rightLeg": {
          "y": 11.48966
        }
      },
      {
        "tick": 69,
        "easing": "INOUTQUAD",
        "rightLeg": {
          "y": 10.938739
        }
      },
      {
        "tick": 3,
        "easing": "INOUTQUAD",
        "rightLeg": {
          "z": -0.14378881
        }
      },
      {
        "tick": 8,
        "easing": "INOUTQUAD",
        "rightLeg": {
          "z": -0.6704929
        }
      },
      {
        "tick": 42,
        "easing": "INOUTQUAD",
        "rightLeg": {
          "z": -0.78942823
        }
      },
      {
        "tick": 69,
        "easing": "INOUTQUAD",
        "rightLeg": {
          "z": -0.6704929
        }
      },
      {
        "tick": 3,
        "easing": "INOUTQUAD",
        "rightLeg": {
          "pitch": -1.229657
        }
      },
      {
        "tick": 8,
        "easing": "INOUTQUAD",
        "rightLeg": {
          "pitch": -2.9106836
        }
      },
      {
        "tick": 42,
        "easing": "INOUTQUAD",
        "rightLeg": {
          "pitch": -2.94779
        }
      },
      {
        "tick": 69,
        "easing": "INOUTQUAD",
        "rightLeg": {
          "pitch": -2.9106836
        }
      },
      {
        "tick": 3,
        "easing": "INOUTQUAD",
        "rightLeg": {
          "yaw": 0.8833633
        }
      },
      {
        "tick": 8,
        "easing": "INOUTQUAD",
        "rightLeg": {
          "yaw": 0.8909206
        }
      },
      {
        "tick": 42,
        "easing": "INOUTQUAD",
        "rightLeg": {
          "yaw": 0.8635948
        }
      },
      {
        "tick": 69,
        "easing": "INOUTQUAD",
        "rightLeg": {
          "yaw": 0.8909206
        }
      },
      {
        "tick": 3,
        "easing": "INOUTQUAD",
        "rightLeg": {
          "roll": -0.010654926
        }
      },
      {
        "tick": 8,
        "easing": "INOUTQUAD",
        "rightLeg": {
          "roll": -1.075182
        }
      },
      {
        "tick": 42,
        "easing": "INOUTQUAD",
        "rightLeg": {
          "roll": -1.0898476
        }
      },
      {
        "tick": 69,
        "easing": "INOUTQUAD",
        "rightLeg": {
          "roll": -1.075182
        }
      },
      {
        "tick": 8,
        "easing": "INOUTQUAD",
        "rightLeg": {
          "bend": 1.5707964
        }
      },
      {
        "tick": 8,
        "easing": "INOUTQUAD",
        "rightArm": {
          "x": -3.3246434
        }
      },
      {
        "tick": 42,
        "easing": "INOUTQUAD",
        "rightArm": {
          "x": -3.3159096
        }
      },
      {
        "tick": 69,
        "easing": "INOUTQUAD",
        "rightArm": {
          "x": -3.3246434
        }
      },
      {
        "tick": 8,
        "easing": "INOUTQUAD",
        "rightArm": {
          "y": 3.5574856
        }
      },
      {
        "tick": 42,
        "easing": "INOUTQUAD",
        "rightArm": {
          "y": 3.6797
        }
      },
      {
        "tick": 69,
        "easing": "INOUTQUAD",
        "rightArm": {
          "y": 3.5574856
        }
      },
      {
        "tick": 8,
        "easing": "INOUTQUAD",
        "rightArm": {
          "z": -3.4333553
        }
      },
      {
        "tick": 42,
        "easing": "INOUTQUAD",
        "rightArm": {
          "z": -3.5943348
        }
      },
      {
        "tick": 69,
        "easing": "INOUTQUAD",
        "rightArm": {
          "z": -3.4333553
        }
      },
      {
        "tick": 8,
        "easing": "INOUTQUAD",
        "rightArm": {
          "pitch": -1.0903721
        }
      },
      {
        "tick": 42,
        "easing": "INOUTQUAD",
        "rightArm": {
          "pitch": -1.06444
        }
      },
      {
        "tick": 69,
        "easing": "INOUTQUAD",
        "rightArm": {
          "pitch": -1.0903721
        }
      },
      {
        "tick": 8,
        "easing": "INOUTQUAD",
        "rightArm": {
          "yaw": -0.40548143
        }
      },
      {
        "tick": 42,
        "easing": "INOUTQUAD",
        "rightArm": {
          "yaw": -0.41184625
        }
      },
      {
        "tick": 69,
        "easing": "INOUTQUAD",
        "rightArm": {
          "yaw": -0.40548143
        }
      },
      {
        "tick": 8,
        "easing": "INOUTQUAD",
        "rightArm": {
          "roll": 0.8053438
        }
      },
      {
        "tick": 42,
        "easing": "INOUTQUAD",
        "rightArm": {
          "roll": 0.80424607
        }
      },
      {
        "tick": 69,
        "easing": "INOUTQUAD",
        "rightArm": {
          "roll": 0.8053438
        }
      },
      {
        "tick": 8,
        "easing": "INOUTQUAD",
        "leftArm": {
          "x": 5.2743835
        }
      },
      {
        "tick": 42,
        "easing": "INOUTQUAD",
        "leftArm": {
          "x": 5.5849085
        }
      },
      {
        "tick": 69,
        "easing": "INOUTQUAD",
        "leftArm": {
          "x": 5.2743835
        }
      },
      {
        "tick": 8,
        "easing": "INOUTQUAD",
        "leftArm": {
          "y": 2.065609
        }
      },
      {
        "tick": 42,
        "easing": "INOUTQUAD",
        "leftArm": {
          "y": 2.6353426
        }
      },
      {
        "tick": 69,
        "easing": "INOUTQUAD",
        "leftArm": {
          "y": 2.065609
        }
      },
      {
        "tick": 8,
        "easing": "INOUTQUAD",
        "leftArm": {
          "z": 1.669417
        }
      },
      {
        "tick": 42,
        "easing": "INOUTQUAD",
        "leftArm": {
          "z": 1.727514
        }
      },
      {
        "tick": 69,
        "easing": "INOUTQUAD",
        "leftArm": {
          "z": 1.669417
        }
      },
      {
        "tick": 8,
        "easing": "INOUTQUAD",
        "leftArm": {
          "pitch": -0.26120487
        }
      },
      {
        "tick": 42,
        "easing": "INOUTQUAD",
        "leftArm": {
          "pitch": -0.15845932
        }
      },
      {
        "tick": 69,
        "easing": "INOUTQUAD",
        "leftArm": {
          "pitch": -0.26120487
        }
      },
      {
        "tick": 8,
        "easing": "INOUTQUAD",
        "leftArm": {
          "yaw": 0.6279764
        }
      },
      {
        "tick": 42,
        "easing": "INOUTQUAD",
        "leftArm": {
          "yaw": 0.5752348
        }
      },
      {
        "tick": 69,
        "easing": "INOUTQUAD",
        "leftArm": {
          "yaw": 0.6279764
        }
      },
      {
        "tick": 8,
        "easing": "INOUTQUAD",
        "leftArm": {
          "roll": -1.0373937
        }
      },
      {
        "tick": 42,
        "easing": "INOUTQUAD",
        "leftArm": {
          "roll": -0.84722865
        }
      },
      {
        "tick": 69,
        "easing": "INOUTQUAD",
        "leftArm": {
          "roll": -1.0373937
        }
      },
      {
        "tick": 8,
        "easing": "INOUTQUAD",
        "leftArm": {
          "bend": -0.9773175
        }
      },
      {
        "tick": 42,
        "easing": "INOUTQUAD",
        "leftArm": {
          "bend": -1.0555179
        }
      },
      {
        "tick": 69,
        "easing": "INOUTQUAD",
        "leftArm": {
          "bend": -0.9773175
        }
      },
      {
        "tick": 3,
        "easing": "INOUTQUAD",
        "leftLeg": {
          "x": 2.4766374
        }
      },
      {
        "tick": 8,
        "easing": "INOUTQUAD",
        "leftLeg": {
          "x": 3.7224581
        }
      },
      {
        "tick": 42,
        "easing": "INOUTQUAD",
        "leftLeg": {
          "x": 3.7578793
        }
      },
      {
        "tick": 69,
        "easing": "INOUTQUAD",
        "leftLeg": {
          "x": 3.7224581
        }
      },
      {
        "tick": 3,
        "easing": "INOUTQUAD",
        "leftLeg": {
          "y": 11.942461
        }
      },
      {
        "tick": 8,
        "easing": "INOUTQUAD",
        "leftLeg": {
          "y": 11.818148
        }
      },
      {
        "tick": 42,
        "easing": "INOUTQUAD",
        "leftLeg": {
          "y": 12.65966
        }
      },
      {
        "tick": 69,
        "easing": "INOUTQUAD",
        "leftLeg": {
          "y": 11.818148
        }
      },
      {
        "tick": 3,
        "easing": "INOUTQUAD",
        "leftLeg": {
          "z": -0.67376137
        }
      },
      {
        "tick": 8,
        "easing": "INOUTQUAD",
        "leftLeg": {
          "z": -1.9133688
        }
      },
      {
        "tick": 42,
        "easing": "INOUTQUAD",
        "leftLeg": {
          "z": -2.0887346
        }
      },
      {
        "tick": 69,
        "easing": "INOUTQUAD",
        "leftLeg": {
          "z": -1.9133688
        }
      },
      {
        "tick": 3,
        "easing": "INOUTQUAD",
        "leftLeg": {
          "pitch": -1.2292633
        }
      },
      {
        "tick": 8,
        "easing": "INOUTQUAD",
        "leftLeg": {
          "pitch": -2.3271315
        }
      },
      {
        "tick": 42,
        "easing": "INOUTQUAD",
        "leftLeg": {
          "pitch": -2.3681767
        }
      },
      {
        "tick": 69,
        "easing": "INOUTQUAD",
        "leftLeg": {
          "pitch": -2.3271315
        }
      },
      {
        "tick": 3,
        "easing": "INOUTQUAD",
        "leftLeg": {
          "yaw": -0.49828458
        }
      },
      {
        "tick": 8,
        "easing": "INOUTQUAD",
        "leftLeg": {
          "yaw": -0.4936605
        }
      },
      {
        "tick": 42,
        "easing": "INOUTQUAD",
        "leftLeg": {
          "yaw": -0.45146012
        }
      },
      {
        "tick": 69,
        "easing": "INOUTQUAD",
        "leftLeg": {
          "yaw": -0.4936605
        }
      },
      {
        "tick": 3,
        "easing": "INOUTQUAD",
        "leftLeg": {
          "roll": 0.14151399
        }
      },
      {
        "tick": 8,
        "easing": "INOUTQUAD",
        "leftLeg": {
          "roll": 0.61023563
        }
      },
      {
        "tick": 42,
        "easing": "INOUTQUAD",
        "leftLeg": {
          "roll": 0.6503308
        }
      },
      {
        "tick": 69,
        "easing": "INOUTQUAD",
        "leftLeg": {
          "roll": 0.61023563
        }
      },
      {
        "tick": 3,
        "easing": "INOUTQUAD",
        "leftLeg": {
          "bend": 0.49798426
        }
      },
      {
        "tick": 8,
        "easing": "INOUTQUAD",
        "leftLeg": {
          "bend": 1.5707964
        }
      },
      {
        "tick": 2,
        "easing": "INOUTQUAD",
        "body": {
          "x": 0.0
        }
      },
      {
        "tick": 8,
        "easing": "INOUTQUAD",
        "body": {
          "x": 0.0
        }
      },
      {
        "tick": 69,
        "easing": "INOUTQUAD",
        "body": {
          "x": 0.0
        }
      },
      {
        "tick": 2,
        "easing": "INOUTQUAD",
        "body": {
          "y": 0.10871734
        }
      },
      {
        "tick": 6,
        "easing": "INOUTQUAD",
        "body": {
          "y": -0.3727083
        }
      },
      {
        "tick": 8,
        "easing": "INOUTQUAD",
        "body": {
          "y": -0.34646413
        }
      },
      {
        "tick": 42,
        "easing": "INOUTQUAD",
        "body": {
          "y": -0.30760708
        }
      },
      {
        "tick": 69,
        "easing": "INOUTQUAD",
        "body": {
          "y": -0.34646413
        }
      },
      {
        "tick": 2,
        "easing": "INOUTQUAD",
        "body": {
          "z": 0.07478854
        }
      },
      {
        "tick": 6,
        "easing": "INOUTQUAD",
        "body": {
          "z": 0.2884701
        }
      },
      {
        "tick": 8,
        "easing": "INOUTQUAD",
        "body": {
          "z": 0.2884701
        }
      },
      {
        "tick": 42,
        "easing": "INOUTQUAD",
        "body": {
          "z": 0.26501256
        }
      },
      {
        "tick": 69,
        "easing": "INOUTQUAD",
        "body": {
          "z": 0.2884701
        }
      },
      {
        "tick": 2,
        "easing": "INOUTQUAD",
        "body": {
          "pitch": -0.19572067
        }
      },
      {
        "tick": 6,
        "easing": "INOUTQUAD",
        "body": {
          "pitch": -0.75492257
        }
      },
      {
        "tick": 8,
        "easing": "INOUTQUAD",
        "body": {
          "pitch": -0.75492257
        }
      },
      {
        "tick": 42,
        "easing": "INOUTQUAD",
        "body": {
          "pitch": -0.80846804
        }
      },
      {
        "tick": 69,
        "easing": "INOUTQUAD",
        "body": {
          "pitch": -0.75492257
        }
      },
      {
        "tick": 2,
        "easing": "INOUTQUAD",
        "body": {
          "yaw": 0.10181806
        }
      },
      {
        "tick": 6,
        "easing": "INOUTQUAD",
        "body": {
          "yaw": 0.39272678
        }
      },
      {
        "tick": 8,
        "easing": "INOUTQUAD",
        "body": {
          "yaw": 0.39272678
        }
      },
      {
        "tick": 42,
        "easing": "INOUTQUAD",
        "body": {
          "yaw": 0.38758522
        }
      },
      {
        "tick": 69,
        "easing": "INOUTQUAD",
        "body": {
          "yaw": 0.39272678
        }
      },
      {
        "tick": 2,
        "easing": "INOUTQUAD",
        "body": {
          "roll": -0.049029004
        }
      },
      {
        "tick": 6,
        "easing": "INOUTQUAD",
        "body": {
          "roll": -0.18911184
        }
      },
      {
        "tick": 8,
        "easing": "INOUTQUAD",
        "body": {
          "roll": -0.18911184
        }
      },
      {
        "tick": 42,
        "easing": "INOUTQUAD",
        "body": {
          "roll": -0.21075182
        }
      },
      {
        "tick": 69,
        "easing": "INOUTQUAD",
        "body": {
          "roll": -0.18911184
        }
      }
    ]
  }
}